MANIFEST.in
README.rst
requirements.txt
setup.cfg
setup.py
cspark/ContextBuilder.py
cspark/ContextEngine.py
cspark/ContextRouter.py
cspark/ContextUpdateHandler.py
cspark/EventTypeRouter.py
cspark/MessageResponse.py
cspark/MessageUpdate.py
cspark/Response.py
cspark/Router.py
cspark/SQLiteContextEngine.py
cspark/Update.py
cspark/UpdateHandler.py
cspark/Updater.py
cspark/__init__.py
cspark_python.egg-info/PKG-INFO
cspark_python.egg-info/SOURCES.txt
cspark_python.egg-info/dependency_links.txt
cspark_python.egg-info/requires.txt
cspark_python.egg-info/top_level.txt